odoo/addons/sm_carsharing_structure_sommobilitat/__init__.py
odoo/addons/sm_carsharing_structure_sommobilitat/__manifest__.py
odoo/addons/sm_carsharing_structure_sommobilitat/models/__init__.py
odoo/addons/sm_carsharing_structure_sommobilitat/models/models_cs_car.py
odoo/addons/sm_carsharing_structure_sommobilitat/security/ir.model.access.csv
odoo/addons/sm_carsharing_structure_sommobilitat/views/views_cs_car.xml
odoo11_addon_sm_carsharing_structure_sommobilitat-11.0.0.0.2.dist-info/METADATA
odoo11_addon_sm_carsharing_structure_sommobilitat-11.0.0.0.2.dist-info/WHEEL
odoo11_addon_sm_carsharing_structure_sommobilitat-11.0.0.0.2.dist-info/top_level.txt
odoo11_addon_sm_carsharing_structure_sommobilitat-11.0.0.0.2.dist-info/RECORD
